orbita/__init__.py
orbita/orbita.py
orbita-0.3.1.dist-info/LICENSE
orbita-0.3.1.dist-info/METADATA
orbita-0.3.1.dist-info/WHEEL
orbita-0.3.1.dist-info/top_level.txt
orbita-0.3.1.dist-info/RECORD
