Metadata-Version: 2.1
Name: orbita
Version: 0.3.1
Summary: Library used to control the Orbita actuator
Home-page: https://github.com/pollen-robotics/orbita
Author: Pollen Robotics
Author-email: contact@pollen-robotics.com
License: UNKNOWN
Platform: UNKNOWN
Requires-Dist: numpy
Requires-Dist: pyquaternion
Provides-Extra: test
Requires-Dist: scipy (>=1.4.0) ; extra == 'test'
